platypus/__init__.py
platypus/bot.py
platypus/commands.py
platypus/meta.py
platypus/paginator.py
platypus/virtualconsole.py
Platypus_discord-0.1.0.dist-info/LICENSE
Platypus_discord-0.1.0.dist-info/METADATA
Platypus_discord-0.1.0.dist-info/WHEEL
Platypus_discord-0.1.0.dist-info/dependency_links.txt
Platypus_discord-0.1.0.dist-info/top_level.txt
Platypus_discord-0.1.0.dist-info/RECORD
